fab_support/__init__.py
fab_support/_version.py
fab_support/command_line.py
fab_support/env_support.py
fab_support/heroku.py
fab_support/heroku_utils.py
fab_support/pelican.py
fab_support/platform_support.py
fab_support/stages_support.py
fab_support/utils.py
fab_support-0.3.5.dist-info/AUTHORS.rst
fab_support-0.3.5.dist-info/LICENSE
fab_support-0.3.5.dist-info/METADATA
fab_support-0.3.5.dist-info/WHEEL
fab_support-0.3.5.dist-info/entry_points.txt
fab_support-0.3.5.dist-info/top_level.txt
fab_support-0.3.5.dist-info/RECORD
