Metadata-Version: 2.1
Name: fab-support
Version: 0.3.5
Summary: Implement staging in Fabric and recipes for pelican to [local, s3] and Django to Heroku.
Home-page: https://github.com/drummonds/fab_support
Author: Humphrey Drummond
Author-email: hum3@drummond.info
License: UNKNOWN
Keywords: fab-support
Platform: UNKNOWN
Classifier: Development Status :: 3 - Alpha
Classifier: Intended Audience :: Developers
Classifier: License :: OSI Approved :: MIT License
Classifier: Natural Language :: English
Classifier: Programming Language :: Python :: 3
Classifier: Programming Language :: Python :: 3.6
